daisy_vis/__init__.py
daisy_vis/animate/__init__.py
daisy_vis/animate/animate_depth_timeseries.py
daisy_vis/animate/test/__init__.py
daisy_vis/animate/test/conftest.py
daisy_vis/animate/test/test_animate_depth_timeseries.py
daisy_vis/io/__init__.py
daisy_vis/io/dlf.py
daisy_vis/io/test/__init__.py
daisy_vis/io/test/test_dlf.py
daisy_vis/plot/__init__.py
daisy_vis/plot/bar.py
daisy_vis/plot/base_plotter.py
daisy_vis/plot/plot_annual.py
daisy_vis/plot/plot_daily.py
daisy_vis/plot/points_and_lines.py
daisy_vis/plot/test/__init__.py
daisy_vis/plot/test/conftest.py
daisy_vis/plot/test/test_bar.py
daisy_vis/plot/test/test_plot_annual.py
daisy_vis/plot/test/test_plot_daily.py
daisy_vis/plot/test/test_points_and_lines.py
daisy_vis/test_helpers/__init__.py
daisy_vis/test_helpers/compare_images.py
daisy_vis/test_helpers/save_animation.py
daisy_vis/test_helpers/test/__init__.py
daisy_vis/test_helpers/test/test_compare_images.py
daisy_vis/transform/__init__.py
daisy_vis/transform/daisy_time_to_timestamp.py
daisy_vis/transform/depth_wide_to_long.py
daisy_vis/transform/test/__init__.py
daisy_vis/transform/test/conftest.py
daisy_vis/transform/test/test_daisy_time_to_timestamp.py
daisy_vis/transform/test/test_depth_wide_to_long.py
doc/animate/animate_depth_dependent.py
doc/io/read_and_print_dlf.py
doc/plot/plot_annual_values.py
doc/plot/plot_daily_values.py
daisy_vis-0.2.0.dist-info/LICENSE
daisy_vis-0.2.0.dist-info/METADATA
daisy_vis-0.2.0.dist-info/WHEEL
daisy_vis-0.2.0.dist-info/top_level.txt
daisy_vis-0.2.0.dist-info/RECORD
