Metadata-Version: 2.1
Name: daisy_vis
Version: 0.2.0
Summary: Visualization module for Daisy log files (dlf)
Author: Silas Nyboe Ørting
Author-email: silas@di.ku.dk
License: GNU General Public License v3 or later (GPLv3+)
Platform: any
Classifier: Development Status :: 4 - Beta
Classifier: License :: OSI Approved :: GNU General Public License v3 or later (GPLv3+)
Classifier: Programming Language :: Python :: 3
License-File: LICENSE
Requires-Dist: pandas
Requires-Dist: matplotlib
Requires-Dist: plotly
Requires-Dist: dash
Provides-Extra: lint
Requires-Dist: pylint ; extra == 'lint'
Requires-Dist: pytest ; extra == 'lint'
Requires-Dist: pillow ; extra == 'lint'
Provides-Extra: test
Requires-Dist: coverage ; extra == 'test'
Requires-Dist: pytest ; extra == 'test'
Requires-Dist: pytest-mpl ; extra == 'test'
Requires-Dist: kaleido ; extra == 'test'
Requires-Dist: pillow ; extra == 'test'
